{"tiles": [{"type": "LISTING_USED_HIGHLIGHT", "data": {"id": 367660623, "inclusionType": "DEFAULT", "listingSource": "sm360-1", "listingTitle": "2024 Audi A5 Sportback quattro Prestige S Line 45 TFSI AWD", "makeName": "Audi", "modelName": "A5 Sportback", "makeId": "m19", "modelId": "d2508", "carYear": 2024, "trimName": "quattro Prestige S Line 45 TFSI AWD", "localizedTransmission": "Automatic", "bodyTypeGroupId": "bg6", "bodyTypeName": "Sedan", "salesStatus": "PAYING", "mileage": 20399, "mileageString": "20,399", "unitMileage": {"value": 20399.0, "unit": "KILOMETERS"}, "exteriorColorName": "Mythos Black Metallic", "normalizedExteriorColor": "BLACK", "price": 54995.0, "priceString": "$54,995", "expectedPrice": 57030, "expectedPriceString": "$57,030", "priceDifferential": 2035.0, "priceDifferentialString": "$2,035", "dealScore": 0.6549268785280835, "daysOnMarket": 566, "dealRating": "GOOD_PRICE", "isFeatured": true, "featuredTypes": ["FEATURED", "PRIORITY", "HIGHLIGHT"], "featuredPremiumType": "PRIORITY", "pictureCount": 0, "originalPictureData": {"url": "https://static.cargurus.com/images/forsale/2025/04/10/08/54/2024_audi_a5_sportback-pic-8498113162179022065-1024x768.jpeg", "height": 768, "width": 1024}, "sellerId": 1470115, "listingPartnerId": 271, "sellerType": "DEALER", "dealerName": "Audi Lauzon", "sellerCity": "Laval, QC", "sellerRegion": "QC", "sellerPostalCode": "H7T 2W3", "distance": 15.916202, "googleStaticMapUrl": "https://www.google.com/maps/dir/?api=1&destination=Audi+Lauzon+2400+Boul+Chomedey%2CLaval+QC%2C+H7T+2W3%2CCA", "serviceProviderId": 378863, "isFranchiseDealer": true, "franchiseMake": "Audi", "debugInfo": " / rank #: 54 / sellerId: 1470115 / spId: 378863 / Paid Dealer: true / active partners: 271", "serviceProviderName": "Audi Lauzon", "phoneNumber": "+1 450-823-3240", "phoneNumberString": "(450) 823-3240", "localizedDriveTrain": "All-Wheel Drive", "localizedExteriorColor": "Mythos Black Metallic", "localizedInteriorColor": "Black", "sellerRating": 4.33, "reviewCount": 27, "isNationwideShipperDealer": true, "howToShop": "PICK_UP_ONLY", "dealerLogoUrl": "https://static.cargurus.com/images/site/2025/02/27/16/50/audi_lauzon-pic-5624518537948919291-200x200.jpeg", "offset": 0, "cityFuelEconomy": {"value": 9.8, "unit": "L_PER_100KM"}, "highwayFuelEconomy": {"value": 7.4, "unit": "L_PER_100KM"}, "combinedFuelEconomy": {"value": 8.72, "unit": "L_PER_100KM"}, "localizedFuelEconomy": ["9.8", "L_PER_100KM"], "localizedFuelType": "Gasoline", "localizedCombinedFuelEconomy": "9 L/100km", "evBatteryDto": {}, "localizedDoors": "4 doors", "driveTrain": "ALL_WHEEL_DRIVE", "localizedEngineDisplayName": "261 hp 2L I4", "ncapOverallSafetyRating": "Not Rated", "vin": "WAUEACF51RA007745", "stockNumber": "R0112(CP)", "interiorColor": "Black"}}, {"type": "LISTING_USED_STANDARD", "data": {"id": 411968898, "inclusionType": "DEFAULT", "listingSource": "sm360-1", "listingTitle": "2021 Chevrolet Silverado 1500 Custom Trail Boss Crew Cab 4WD", "makeName": "Chevrolet", "modelName": "Silverado 1500", "makeId": "m1", "modelId": "d630", "carYear": 2021, "trimName": "Custom Trail Boss Crew Cab 4WD", "localizedTransmission": "Automatic", "bodyTypeGroupId": "bg5", "bodyTypeName": "Pickup Truck", "salesStatus": "PAYING", "options": ["Alloy Wheels", "Bluetooth", "Backup Camera", "Remote Start", "Android Auto", "CarPlay"], "mileage": 119102, "mileageString": "119,102", "unitMileage": {"value": 119102.0, "unit": "KILOMETERS"}, "exteriorColorName": "Red", "normalizedExteriorColor": "RED", "price": 39995.0, "priceString": "$39,995", "expectedPrice": 39995, "expectedPriceString": "$39,995", "priceDifferential": 0.0, "priceDifferentialString": "$0", "dealScore": 0.04102067776948687, "daysOnMarket": 21, "dealRating": "FAIR_PRICE", "pictureCount": 0, "originalPictureData": {"url": "https://static.cargurus.com/images/forsale/2025/04/03/09/16/2021_chevrolet_silverado_1500-pic-6702999612712635249-1024x768.jpeg", "height": 768, "width": 1024}, "sellerId": 1778108, "listingPartnerId": 271, "sellerType": "DEALER", "dealerName": "St-Jerome Chevrolet Buick GMC", "sellerCity": "Saint-jerome, QC", "sellerRegion": "QC", "sellerPostalCode": "J7Y 4B5", "distance": 46.343376, "googleStaticMapUrl": "https://www.google.com/maps/dir/?api=1&destination=St-Jerome+Chevrolet+Buick+GMC+265%2C+Rue+John-F.+Kennedy%2CSaint-jerome+QC%2C+J7Y+4B5%2CCA", "serviceProviderId": 361336, "isFranchiseDealer": true, "franchiseMake": "Chevrolet", "isCPO": true, "debugInfo": " / rank #: 6621 / sellerId: 1778108 / spId: 361336 / Paid Dealer: true / active partners: 271", "serviceProviderName": "St-Jerome Chevrolet Buick GMC", "phoneNumber": "+1 450-497-0134", "phoneNumberString": "(450) 497-0134", "localizedDriveTrain": "Four-Wheel Drive", "localizedExteriorColor": "Red", "localizedInteriorColor": "Gray", "sellerRating": 4.43, "reviewCount": 58, "howToShop": "PICK_UP_ONLY", "dealerLogoUrl": "https://static.cargurus.com/images/site/2023/02/08/09/37/st-jerome_chevrolet_buick_gmc-pic-4106370824850913285-200x200.jpeg", "offset": 6621, "cityFuelEconomy": {"value": 18.1, "unit": "L_PER_100KM"}, "highwayFuelEconomy": {"value": 13.1, "unit": "L_PER_100KM"}, "combinedFuelEconomy": {"value": 15.85, "unit": "L_PER_100KM"}, "localizedFuelEconomy": ["18.1", "L_PER_100KM"], "localizedFuelType": "Gasoline", "localizedCombinedFuelEconomy": "16 L/100km", "evBatteryDto": {}, "localizedDoors": "4 doors", "driveTrain": "FOUR_WHEEL_DRIVE", "localizedEngineDisplayName": "355 hp 5.3L V8", "ncapOverallSafetyRating": "4", "vin": "1GCPYCEF9MZ319632", "stockNumber": "25901A", "interiorColor": "Gray"}}, {"type": "LISTING_USED_STANDARD", "data": {"id": 412830643, "inclusionType": "DEFAULT", "listingSource": "HGr\u00e9goire-1", "listingTitle": "2023 Kia EV6 GT AWD", "makeName": "Kia", "modelName": "EV6", "makeId": "m33", "modelId": "d3127", "carYear": 2023, "trimName": "GT AWD", "localizedTransmission": "Automatic", "bodyTypeGroupId": "bg7", "bodyTypeName": "SUV / Crossover", "salesStatus": "PAYING", "options": ["Sunroof/Moonroof", "Navigation System", "Bluetooth", "Backup Camera", "Heated Seats"], "mileage": 22923, "mileageString": "22,923", "unitMileage": {"value": 22923.0, "unit": "KILOMETERS"}, "exteriorColorName": "Black", "normalizedExteriorColor": "BLACK", "price": 48895.0, "priceString": "$48,895", "expectedPrice": 48790, "expectedPriceString": "$48,790", "priceDifferential": -105.0, "priceDifferentialString": "$105", "dealScore": 0.04070636104368741, "daysOnMarket": 13, "dealRating": "FAIR_PRICE", "isFeatured": true, "featuredTypes": ["FEATURED", "PRIORITY"], "featuredPremiumType": "PRIORITY", "pictureCount": 0, "originalPictureData": {"url": "https://static.cargurus.com/images/forsale/2025/04/04/07/35/2023_kia_ev6-pic-4646143007646973871-1024x768.jpeg", "height": 768, "width": 1024}, "sellerId": 2191112, "listingPartnerId": 304, "sellerType": "DEALER", "dealerName": "HGregoire Blainville Signature", "sellerCity": "Blainville, QC", "sellerRegion": "QC", "sellerPostalCode": "J7C 2P2", "distance": 33.59067, "googleStaticMapUrl": "https://www.google.com/maps/dir/?api=1&destination=HGregoire+Blainville+Signature+1384+Boulevard+du+Cure-Labelle%2CBlainville+QC%2C+J7C+2P2%2CCA", "serviceProviderId": 452248, "isFranchiseDealer": true, "franchiseMake": "Nissan", "debugInfo": " / rank #: 6622 / sellerId: 2191112 / spId: 452248 / Paid Dealer: true / active partners: 304", "serviceProviderName": "HGregoire Blainville Signature", "phoneNumber": "+1 587-805-1514", "phoneNumberString": "(587) 805-1514", "localizedDriveTrain": "All-Wheel Drive", "localizedExteriorColor": "Black", "localizedInteriorColor": "Black", "sellerRating": 5.0, "reviewCount": 2, "howToShop": "PICK_UP_ONLY", "dealerLogoUrl": "https://static.cargurus.com/images/site/2023/11/09/21/56/hgregoire_blainville_signature-pic-14857770593886294853-200x200.jpeg", "offset": 6622, "cityFuelEconomy": {"value": 2.8, "unit": "L_PER_100KM"}, "highwayFuelEconomy": {"value": 3.2, "unit": "L_PER_100KM"}, "combinedFuelEconomy": {"value": 2.98, "unit": "L_PER_100KM"}, "localizedFuelEconomy": ["2.8", "L_PER_100KM"], "localizedFuelType": "Electric", "localizedCombinedFuelEconomy": "3 L/100km", "evBatteryDto": {"chargingTime240V": "7 hr", "chargingTime120V": "68 hr", "capacity": "77.4 kWh", "range": "373 km"}, "localizedDoors": "4 doors", "driveTrain": "ALL_WHEEL_DRIVE", "localizedEngineDisplayName": "Electric", "ncapOverallSafetyRating": "Not Rated", "vin": "KNDC5DLE8P5120414", "stockNumber": "QE40554", "interiorColor": "Black"}}, {"type": "LISTING_USED_STANDARD", "data": {"id": 406578803, "inclusionType": "DEFAULT", "listingSource": "sm360-1", "listingTitle": "2022 Audi S3 2.0T quattro Komfort AWD", "makeName": "Audi", "modelName": "S3", "makeId": "m19", "modelId": "d1183", "carYear": 2022, "trimName": "2.0T quattro Komfort AWD", "localizedTransmission": "Automatic", "bodyTypeGroupId": "bg6", "bodyTypeName": "Sedan", "salesStatus": "PAYING", "options": ["Leather Seats", "Sunroof/Moonroof", "Alloy Wheels", "Bluetooth", "Backup Camera", "Heated Seats", "Android Auto", "CarPlay", "Multi Zone Climate Control"], "mileage": 78534, "mileageString": "78,534", "unitMileage": {"value": 78534.0, "unit": "KILOMETERS"}, "exteriorColorName": "Glacier White Metallic", "normalizedExteriorColor": "WHITE", "price": 36771.0, "priceString": "$36,771", "expectedPrice": 37194, "expectedPriceString": "$37,194", "priceDifferential": 423.0, "priceDifferentialString": "$423", "dealScore": 0.040397496048561354, "daysOnMarket": 83, "dealRating": "FAIR_PRICE", "isFeatured": true, "featuredTypes": ["FEATURED", "PRIORITY"], "featuredPremiumType": "PRIORITY", "pictureCount": 0, "originalPictureData": {"url": "https://static.cargurus.com/images/forsale/2025/01/24/08/07/2022_audi_s3-pic-2235520003423462494-1024x768.jpeg", "height": 768, "width": 1024}, "sellerId": 2140832, "listingPartnerId": 271, "sellerType": "DEALER", "dealerName": "Drummondville Volkswagen", "sellerCity": "Drummondville, QC", "sellerRegion": "QC", "sellerPostalCode": "J2C 8N1", "distance": 95.09152, "googleStaticMapUrl": "https://www.google.com/maps/dir/?api=1&destination=Drummondville+Volkswagen+30+Rue+Robert+Bernard%2CDrummondville+QC%2C+J2C+8N1%2CCA", "serviceProviderId": 358714, "isFranchiseDealer": true, "franchiseMake": "Volkswagen", "debugInfo": " / rank #: 6623 / sellerId: 2140832 / spId: 358714 / Paid Dealer: true / active partners: 271", "serviceProviderName": "Drummondville Volkswagen", "phoneNumber": "+1 365-363-0089", "phoneNumberString": "(365) 363-0089", "localizedExteriorColor": "Glacier White Metallic", "localizedInteriorColor": "Black w/Gray Stitch", "sellerRating": 4.24, "reviewCount": 29, "isNationwideShipperDealer": true, "howToShop": "PICK_UP_ONLY", "dealerLogoUrl": "https://static.cargurus.com/images/site/2023/06/01/14/02/drummondville_volkswagen-pic-2887152266439015011-200x200.jpeg", "offset": 6623, "evBatteryDto": {}, "ncapOverallSafetyRating": "Not Rated", "vin": "WAUG3CGY9NA005098", "stockNumber": "24428B", "interiorColor": "Black w/Gray Stitch"}}, {"type": "LISTING_USED_STANDARD", "data": {"id": 413662993, "inclusionType": "DEFAULT", "listingSource": "Group Gabriel-1", "listingTitle": "2016 Volkswagen Jetta 1.8T Sport FWD", "makeName": "Volkswagen", "modelName": "Jetta", "makeId": "m55", "modelId": "d200", "carYear": 2016, "trimName": "1.8T Sport FWD", "localizedTransmission": "Automatic", "bodyTypeGroupId": "bg6", "bodyTypeName": "Sedan", "salesStatus": "PAYING", "options": ["Sunroof/Moonroof", "Alloy Wheels", "Bluetooth", "Backup Camera", "Heated Seats"], "mileage": 77000, "mileageString": "77,000", "unitMileage": {"value": 77000.0, "unit": "KILOMETERS"}, "exteriorColorName": "Grey", "normalizedExteriorColor": "GRAY", "price": 13997.0, "priceString": "$13,997", "expectedPrice": 14101, "expectedPriceString": "$14,101", "priceDifferential": 104.0, "priceDifferentialString": "$104", "dealScore": 0.04013210840379622, "daysOnMarket": 3, "dealRating": "FAIR_PRICE", "isFeatured": true, "featuredTypes": ["FEATURED", "PRIORITY"], "featuredPremiumType": "PRIORITY", "pictureCount": 0, "originalPictureData": {"url": "https://static.cargurus.com/images/forsale/2025/04/12/05/39/2016_volkswagen_jetta-pic-7443523529342685981-1024x768.jpeg", "height": 768, "width": 1024}, "sellerId": 2272715, "listingPartnerId": 630, "sellerType": "DEALER", "dealerName": "Volkswagen Gabriel Chateauguay", "sellerCity": "Chateauguay, QC", "sellerRegion": "QC", "sellerPostalCode": "J6K 3C2", "distance": 18.948435, "googleStaticMapUrl": "https://www.google.com/maps/dir/?api=1&destination=Volkswagen+Gabriel+Chateauguay+252+Boulevard+St-Jean-Baptiste%2CChateauguay+QC%2C+J6K+3C2%2CCA", "serviceProviderId": 456900, "isFranchiseDealer": true, "franchiseMake": "Volkswagen", "debugInfo": " / rank #: 6624 / sellerId: 2272715 / spId: 456900 / Paid Dealer: true / active partners: 630", "serviceProviderName": "Volkswagen Gabriel Chateauguay", "phoneNumber": "+1 450-234-9390", "phoneNumberString": "(450) 234-9390", "phoneNumberSMS": "+18559612800", "supportsSms": true, "localizedDriveTrain": "Front-Wheel Drive", "localizedExteriorColor": "Gray", "sellerRating": 4.0, "reviewCount": 1, "howToShop": "PICK_UP_ONLY", "dealerLogoUrl": "https://static.cargurus.com/images/site/2024/12/06/16/02/volkswagen_gabriel_chateauguay-pic-10694936225886650961-200x200.jpeg", "offset": 6624, "cityFuelEconomy": {"value": 9.4, "unit": "L_PER_100KM"}, "highwayFuelEconomy": {"value": 6.5, "unit": "L_PER_100KM"}, "combinedFuelEconomy": {"value": 8.094999, "unit": "L_PER_100KM"}, "localizedFuelEconomy": ["9.4", "L_PER_100KM"], "localizedFuelType": "Gasoline", "localizedCombinedFuelEconomy": "8 L/100km", "evBatteryDto": {}, "localizedDoors": "4 doors", "driveTrain": "FRONT_WHEEL_DRIVE", "localizedEngineDisplayName": "170 hp 1.8L I4", "ncapOverallSafetyRating": "5", "vin": "3VWD07AJ2GM349893", "stockNumber": "25070A"}}, {"type": "LISTING_USED_STANDARD", "data": {"id": 403430349, "inclusionType": "DEFAULT", "listingSource": "Monezsoft-1", "listingTitle": "2018 Lincoln MKT Reserve AWD", "makeName": "Lincoln", "modelName": "MKT", "makeId": "m38", "modelId": "d2032", "carYear": 2018, "trimName": "Reserve AWD", "localizedTransmission": "Automatic", "bodyTypeGroupId": "bg7", "bodyTypeName": "SUV / Crossover", "salesStatus": "PAYING", "options": ["Sunroof/Moonroof", "Navigation System", "Alloy Wheels", "Bluetooth", "Backup Camera", "Heated Seats"], "mileage": 140082, "mileageString": "140,082", "unitMileage": {"value": 140082.0, "unit": "KILOMETERS"}, "exteriorColorName": "WHITE", "normalizedExteriorColor": "WHITE", "price": 16995.0, "priceString": "$16,995", "expectedPrice": 17022, "expectedPriceString": "$17,022", "priceDifferential": 27.0, "priceDifferentialString": "$27", "dealScore": 0.0396714372953656, "daysOnMarket": 125, "dealRating": "FAIR_PRICE", "isFeatured": true, "featuredTypes": ["FEATURED"], "pictureCount": 0, "originalPictureData": {"url": "https://static.cargurus.com/images/forsale/2024/12/12/06/04/2018_lincoln_mkt-pic-594615923200920664-1024x768.jpeg", "height": 768, "width": 1024}, "sellerId": 2147678, "listingPartnerId": 571, "sellerType": "DEALER", "dealerName": "Classe Auto", "sellerCity": "Montreal, QC", "sellerRegion": "QC", "sellerPostalCode": "H1G 3H2", "distance": 12.272305, "googleStaticMapUrl": "https://www.google.com/maps/dir/?api=1&destination=Classe+Auto+5151+Boulevard+Industriel%2CMontreal+QC%2C+H1G+3H2%2CCA", "serviceProviderId": 395062, "debugInfo": " / rank #: 6625 / sellerId: 2147678 / spId: 395062 / Paid Dealer: true / active partners: 571", "serviceProviderName": "Classe Auto", "phoneNumber": "+1 855-916-3028", "phoneNumberString": "(855) 916-3028", "localizedDriveTrain": "All-Wheel Drive", "localizedExteriorColor": "White", "localizedInteriorColor": "Black", "sellerRating": 4.22, "reviewCount": 27, "isNationwideShipperDealer": true, "howToShop": "PICK_UP_ONLY", "dealerLogoUrl": "https://static.cargurus.com/images/site/2018/08/27/10/12/classe_auto-pic-1704409577497777139-200x200.jpeg", "offset": 6625, "cityFuelEconomy": {"value": 15.7, "unit": "L_PER_100KM"}, "highwayFuelEconomy": {"value": 11.2, "unit": "L_PER_100KM"}, "combinedFuelEconomy": {"value": 13.675, "unit": "L_PER_100KM"}, "localizedFuelEconomy": ["15.7", "L_PER_100KM"], "localizedFuelType": "Gasoline", "localizedCombinedFuelEconomy": "14 L/100km", "evBatteryDto": {}, "localizedDoors": "4 doors", "driveTrain": "ALL_WHEEL_DRIVE", "localizedEngineDisplayName": "365 hp 3.5L V6", "ncapOverallSafetyRating": "Not Rated", "vin": "2LMHJ5AT9JBL02103", "stockNumber": "L02103", "interiorColor": "BLACK"}}, {"type": "LISTING_USED_STANDARD", "data": {"id": 413895560, "inclusionType": "DEFAULT", "listingSource": "D2C media-1", "listingTitle": "2018 RAM 1500", "makeName": "RAM", "modelName": "1500", "makeId": "m191", "modelId": "d2110", "carYear": 2018, "localizedTransmission": "Automatic", "bodyTypeGroupId": "bg5", "bodyTypeName": "Pickup Truck", "salesStatus": "PAYING", "options": ["Adaptive Cruise Control", "Bluetooth", "Backup Camera"], "mileage": 141585, "mileageString": "141,585", "unitMileage": {"value": 141585.0, "unit": "KILOMETERS"}, "exteriorColorName": "Noir", "normalizedExteriorColor": "BLACK", "price": 23995.0, "priceString": "$23,995", "expectedPrice": 23668, "expectedPriceString": "$23,668", "priceDifferential": -327.0, "priceDifferentialString": "$327", "dealScore": 0.03946059949435521, "dealRating": "FAIR_PRICE", "isFeatured": true, "featuredTypes": ["FEATURED"], "pictureCount": 0, "originalPictureData": {"url": "https://static.cargurus.com/images/forsale/2025/04/15/13/04/2018_ram_1500-pic-4063743268233679789-1024x768.jpeg", "height": 768, "width": 1024}, "sellerId": 1279261, "listingPartnerId": 243, "sellerType": "DEALER", "dealerName": "Auto Studio 72", "sellerCity": "Mirabel, QC", "sellerRegion": "QC", "sellerPostalCode": "J7J 1X2", "distance": 36.782818, "googleStaticMapUrl": "https://www.google.com/maps/dir/?api=1&destination=Auto+Studio+72+14460+Rue+Joseph+Marc+Vermette%2CMirabel+QC%2C+J7J+1X2%2CCA", "serviceProviderId": 359099, "debugInfo": " / rank #: 6626 / sellerId: 1279261 / spId: 359099 / Paid Dealer: true / active partners: 243", "serviceProviderName": "Auto Studio 72", "phoneNumber": "+1 867-675-0693", "phoneNumberString": "(867) 675-0693", "localizedExteriorColor": "Black", "sellerRating": 5.0, "reviewCount": 21, "howToShop": "PICK_UP_ONLY", "dealerLogoUrl": "https://static.cargurus.com/images/site/2021/06/17/12/07/auto_studio_72-pic-11041117041902951097-200x200.jpeg", "offset": 6626, "localizedFuelType": "Biodiesel", "evBatteryDto": {}, "localizedEngineDisplayName": "240 hp 3L V6 Biodiesel", "ncapOverallSafetyRating": "4", "vin": "1C6RR7TM1JS310420", "stockNumber": "310420"}}, {"type": "LISTING_USED_STANDARD", "data": {"id": 412999968, "inclusionType": "DEFAULT", "listingSource": "sm360-1", "listingTitle": "2023 Kia Sportage LX FWD", "makeName": "Kia", "modelName": "Sportage", "makeId": "m33", "modelId": "d164", "carYear": 2023, "trimName": "LX FWD", "localizedTransmission": "Automatic", "bodyTypeGroupId": "bg7", "bodyTypeName": "SUV / Crossover", "salesStatus": "PAYING", "options": ["Alloy Wheels", "Bluetooth", "Backup Camera", "Heated Seats", "Android Auto", "CarPlay"], "mileage": 18637, "mileageString": "18,637", "unitMileage": {"value": 18637.0, "unit": "KILOMETERS"}, "exteriorColorName": "Vesta Blue", "normalizedExteriorColor": "BLUE", "price": 26889.0, "priceString": "$26,889", "expectedPrice": 27033, "expectedPriceString": "$27,033", "priceDifferential": 144.0, "priceDifferentialString": "$144", "dealScore": 0.03936643438289089, "daysOnMarket": 11, "dealRating": "FAIR_PRICE", "isFeatured": true, "featuredTypes": ["FEATURED", "PRIORITY"], "featuredPremiumType": "PRIORITY", "pictureCount": 0, "originalPictureData": {"url": "https://static.cargurus.com/images/forsale/2025/04/12/15/33/2023_kia_sportage-pic-8591826729142467478-1024x768.jpeg", "height": 768, "width": 1024}, "sellerId": 2140832, "listingPartnerId": 271, "sellerType": "DEALER", "dealerName": "Drummondville Volkswagen", "sellerCity": "Drummondville, QC", "sellerRegion": "QC", "sellerPostalCode": "J2C 8N1", "distance": 95.09152, "googleStaticMapUrl": "https://www.google.com/maps/dir/?api=1&destination=Drummondville+Volkswagen+30+Rue+Robert+Bernard%2CDrummondville+QC%2C+J2C+8N1%2CCA", "serviceProviderId": 358714, "isFranchiseDealer": true, "franchiseMake": "Volkswagen", "debugInfo": " / rank #: 6627 / sellerId: 2140832 / spId: 358714 / Paid Dealer: true / active partners: 271", "serviceProviderName": "Drummondville Volkswagen", "phoneNumber": "+1 365-363-0089", "phoneNumberString": "(365) 363-0089", "localizedDriveTrain": "Front-Wheel Drive", "localizedExteriorColor": "Vesta Blue", "localizedInteriorColor": "Black", "sellerRating": 4.24, "reviewCount": 29, "isNationwideShipperDealer": true, "howToShop": "PICK_UP_ONLY", "dealerLogoUrl": "https://static.cargurus.com/images/site/2023/06/01/14/02/drummondville_volkswagen-pic-2887152266439015011-200x200.jpeg", "offset": 6627, "cityFuelEconomy": {"value": 9.4, "unit": "L_PER_100KM"}, "highwayFuelEconomy": {"value": 7.4, "unit": "L_PER_100KM"}, "combinedFuelEconomy": {"value": 8.5, "unit": "L_PER_100KM"}, "localizedFuelEconomy": ["9.4", "L_PER_100KM"], "localizedFuelType": "Gasoline", "localizedCombinedFuelEconomy": "9 L/100km", "evBatteryDto": {}, "localizedDoors": "4 doors", "driveTrain": "FRONT_WHEEL_DRIVE", "localizedEngineDisplayName": "187 hp 2.5L I4", "ncapOverallSafetyRating": "Not Rated", "vin": "KNDPU3AF8P7078132", "stockNumber": "D524", "interiorColor": "Black"}}, {"type": "LISTING_USED_STANDARD", "data": {"id": 411980094, "inclusionType": "DEFAULT", "listingSource": "Dealercity.ca-1", "listingTitle": "2014 Kia Sportage LX AWD", "makeName": "Kia", "modelName": "Sportage", "makeId": "m33", "modelId": "d164", "carYear": 2014, "trimName": "LX AWD", "localizedTransmission": "Automatic", "bodyTypeGroupId": "bg7", "bodyTypeName": "SUV / Crossover", "salesStatus": "PAYING", "options": ["Bluetooth"], "mileage": 219000, "mileageString": "219,000", "unitMileage": {"value": 219000.0, "unit": "KILOMETERS"}, "exteriorColorName": "Noir", "normalizedExteriorColor": "BLACK", "price": 6699.0, "priceString": "$6,699", "expectedPrice": 6679, "expectedPriceString": "$6,679", "priceDifferential": -20.0, "priceDifferentialString": "$20", "dealScore": 0.03896566193928136, "daysOnMarket": 21, "dealRating": "FAIR_PRICE", "pictureCount": 0, "originalPictureData": {"url": "https://static.cargurus.com/images/forsale/2025/04/15/17/35/2014_kia_sportage-pic-2732301462443887790-1024x768.jpeg", "height": 768, "width": 1024}, "sellerId": 2258217, "listingPartnerId": 298, "sellerType": "DEALER", "dealerName": "Autos BB", "sellerCity": "Laval, QC", "sellerRegion": "QC", "sellerPostalCode": "H7K 2J8", "distance": 19.650179, "googleStaticMapUrl": "https://www.google.com/maps/dir/?api=1&destination=Autos+BB+5280+Boul+Des+Laurentides%2CLaval+QC%2C+H7K+2J8%2CCA", "serviceProviderId": 358306, "debugInfo": " / rank #: 6628 / sellerId: 2258217 / spId: 358306 / Paid Dealer: true / active partners: 298", "serviceProviderName": "Autos BB", "phoneNumber": "+1 450-235-2868", "phoneNumberString": "(450) 235-2868", "localizedDriveTrain": "All-Wheel Drive", "localizedExteriorColor": "Black", "localizedInteriorColor": "Black", "sellerRating": 4.14, "reviewCount": 64, "howToShop": "PICK_UP_ONLY", "dealerLogoUrl": "https://static.cargurus.com/images/site/2017/03/10/09/45/autos_bb-pic-7968078406793208644-200x200.jpeg", "offset": 6628, "cityFuelEconomy": {"value": 12.4, "unit": "L_PER_100KM"}, "highwayFuelEconomy": {"value": 9.0, "unit": "L_PER_100KM"}, "combinedFuelEconomy": {"value": 10.87, "unit": "L_PER_100KM"}, "localizedFuelEconomy": ["12.4", "L_PER_100KM"], "localizedFuelType": "Gasoline", "localizedCombinedFuelEconomy": "11 L/100km", "evBatteryDto": {}, "localizedDoors": "4 doors", "driveTrain": "ALL_WHEEL_DRIVE", "localizedEngineDisplayName": "182 hp 2.4L I4", "ncapOverallSafetyRating": "4", "vin": "KNDPBCAC2E7590610", "stockNumber": "3108000346-BB", "interiorColor": "Noir"}}, {"type": "LISTING_USED_STANDARD", "data": {"id": 413425423, "inclusionType": "DEFAULT", "listingSource": "eDealer Light-1", "listingTitle": "2018 Cadillac Escalade ESV 4WD", "makeName": "Cadillac", "modelName": "Escalade ESV", "makeId": "m22", "modelId": "d143", "carYear": 2018, "trimName": "4WD", "localizedTransmission": "Automatic", "bodyTypeGroupId": "bg7", "bodyTypeName": "SUV / Crossover", "salesStatus": "PAYING", "options": ["Leather Seats", "Navigation System", "Adaptive Cruise Control", "Alloy Wheels", "Third Row Seating", "Bluetooth", "Backup Camera", "Remote Start", "Parking Sensors", "Heated Seats", "Android Auto", "CarPlay"], "mileage": 122206, "mileageString": "122,206", "unitMileage": {"value": 122206.0, "unit": "KILOMETERS"}, "exteriorColorName": "Black", "normalizedExteriorColor": "BLACK", "price": 39980.0, "priceString": "$39,980", "expectedPrice": 40158, "expectedPriceString": "$40,158", "priceDifferential": 178.0, "priceDifferentialString": "$178", "dealScore": 0.0388358440709865, "daysOnMarket": 6, "dealRating": "FAIR_PRICE", "isFeatured": true, "featuredTypes": ["FEATURED", "PRIORITY"], "featuredPremiumType": "PRIORITY", "pictureCount": 0, "originalPictureData": {"url": "https://static.cargurus.com/images/forsale/2025/04/10/21/10/2018_cadillac_escalade_esv-pic-2732215380611784854-1024x768.jpeg", "height": 768, "width": 1024}, "sellerId": 1078008, "listingPartnerId": 377, "sellerType": "DEALER", "dealerName": "Auto Flash", "sellerCity": "St.-Hubert, QC", "sellerRegion": "QC", "sellerPostalCode": "J3Y 1A5", "distance": 10.853437, "googleStaticMapUrl": "https://www.google.com/maps/dir/?api=1&destination=Auto+Flash+5410+Grande-All%C3%A9e%2CSt.-Hubert+QC%2C+J3Y+1A5%2CCA", "serviceProviderId": 358995, "debugInfo": " / rank #: 6629 / sellerId: 1078008 / spId: 358995 / Paid Dealer: true / active partners: 377", "serviceProviderName": "Auto Flash", "phoneNumber": "+1 855-290-5293", "phoneNumberString": "(855) 290-5293", "localizedDriveTrain": "Four-Wheel Drive", "localizedExteriorColor": "Black", "localizedInteriorColor": "Black", "sellerRating": 4.41, "reviewCount": 123, "howToShop": "HOME_DROP_OFF", "dealerLogoUrl": "https://static.cargurus.com/images/site/2023/02/06/15/40/auto_flash-pic-8455847951499679195-200x200.jpeg", "offset": 6629, "cityFuelEconomy": {"value": 16.8, "unit": "L_PER_100KM"}, "highwayFuelEconomy": {"value": 11.2, "unit": "L_PER_100KM"}, "combinedFuelEconomy": {"value": 14.28, "unit": "L_PER_100KM"}, "localizedFuelEconomy": ["16.8", "L_PER_100KM"], "localizedFuelType": "Gasoline", "localizedCombinedFuelEconomy": "14 L/100km", "evBatteryDto": {}, "localizedDoors": "4 doors", "driveTrain": "FOUR_WHEEL_DRIVE", "localizedEngineDisplayName": "420 hp 6.2L V8", "ncapOverallSafetyRating": "4", "vin": "1GYS4GKJXJR129706", "stockNumber": "25S064", "interiorColor": "Black"}}, {"type": "LISTING_USED_STANDARD", "data": {"id": 413559092, "inclusionType": "DEFAULT", "listingSource": "D2C media-1", "listingTitle": "2023 GMC Sierra 2500HD Pro Crew Cab 4WD", "makeName": "GMC", "modelName": "Sierra 2500HD", "makeId": "m26", "modelId": "d119", "carYear": 2023, "trimName": "Pro Crew Cab 4WD", "localizedTransmission": "Automatic", "bodyTypeGroupId": "bg5", "bodyTypeName": "Pickup Truck", "salesStatus": "PAYING", "options": ["Bluetooth", "Backup Camera"], "mileage": 66970, "mileageString": "66,970", "unitMileage": {"value": 66970.0, "unit": "KILOMETERS"}, "exteriorColorName": "Noir", "normalizedExteriorColor": "BLACK", "price": 61995.0, "priceString": "$61,995", "expectedPrice": 61994, "expectedPriceString": "$61,994", "priceDifferential": -1.0, "priceDifferentialString": "$1", "dealScore": 0.038832416137772566, "daysOnMarket": 4, "dealRating": "FAIR_PRICE", "isFeatured": true, "featuredTypes": ["FEATURED"], "pictureCount": 0, "originalPictureData": {"url": "https://static.cargurus.com/images/forsale/2025/04/11/09/25/2023_gmc_sierra_2500hd-pic-3719135587180435604-1024x768.jpeg", "height": 768, "width": 1024}, "sellerId": 1703227, "listingPartnerId": 243, "sellerType": "DEALER", "dealerName": "Chevrolet Buick GMC de LaSalle", "sellerCity": "Lasalle, QC", "sellerRegion": "QC", "sellerPostalCode": "H8N 1X9", "distance": 6.622868, "googleStaticMapUrl": "https://www.google.com/maps/dir/?api=1&destination=Chevrolet+Buick+GMC+de+LaSalle+8000+boul.+Newman%2CLasalle+QC%2C+H8N+1X9%2CCA", "serviceProviderId": 385094, "isFranchiseDealer": true, "franchiseMake": "GMC", "isCPO": true, "debugInfo": " / rank #: 6630 / sellerId: 1703227 / spId: 385094 / Paid Dealer: true / active partners: 243", "serviceProviderName": "Chevrolet Buick GMC de LaSalle", "phoneNumber": "+1 450-328-5705", "phoneNumberString": "(450) 328-5705", "localizedDriveTrain": "Four-Wheel Drive", "localizedExteriorColor": "Black", "sellerRating": 5.0, "reviewCount": 31, "howToShop": "HOME_DROP_OFF", "dealerLogoUrl": "https://static.cargurus.com/images/site/2023/03/27/15/23/chevrolet_buick_gmc_de_lasalle-pic-8361250431850925619-200x200.jpeg", "offset": 6630, "evBatteryDto": {}, "localizedDoors": "4 doors", "driveTrain": "FOUR_WHEEL_DRIVE", "ncapOverallSafetyRating": "Not Rated", "vin": "1GT19LEY7PF163830", "stockNumber": "U3051"}}, {"type": "LISTING_USED_STANDARD", "data": {"id": 413445714, "inclusionType": "DEFAULT", "listingSource": "Group Gabriel-1", "listingTitle": "2022 Lexus NX 350 Premium AWD", "makeName": "Lexus", "modelName": "NX", "makeId": "m37", "modelId": "d2616", "carYear": 2022, "trimName": "350 Premium AWD", "localizedTransmission": "Automatic", "bodyTypeGroupId": "bg7", "bodyTypeName": "SUV / Crossover", "salesStatus": "PAYING", "options": ["Leather Seats", "Sunroof/Moonroof", "Navigation System", "Alloy Wheels", "Bluetooth", "Backup Camera", "Blind Spot Monitoring", "Parking Sensors", "Heated Seats", "Android Auto", "CarPlay"], "mileage": 33568, "mileageString": "33,568", "unitMileage": {"value": 33568.0, "unit": "KILOMETERS"}, "exteriorColorName": "White", "normalizedExteriorColor": "WHITE", "price": 45995.0, "priceString": "$45,995", "expectedPrice": 46367, "expectedPriceString": "$46,367", "priceDifferential": 372.0, "priceDifferentialString": "$372", "dealScore": 0.038808920106242484, "daysOnMarket": 5, "dealRating": "FAIR_PRICE", "isFeatured": true, "featuredTypes": ["FEATURED", "PRIORITY"], "featuredPremiumType": "PRIORITY", "pictureCount": 0, "originalPictureData": {"url": "https://static.cargurus.com/images/forsale/2025/04/13/02/17/2022_lexus_nx-pic-6273863863608596487-1024x768.jpeg", "height": 768, "width": 1024}, "sellerId": 2255801, "listingPartnerId": 630, "sellerType": "DEALER", "dealerName": "Lexus Gabriel St-Laurent", "sellerCity": "Montr\u00e9al, QC", "sellerRegion": "QC", "sellerPostalCode": "H4N", "distance": 6.453947, "googleStaticMapUrl": "https://www.google.com/maps/dir/?api=1&destination=Lexus+Gabriel+St-Laurent+3303+Chemin+de+la+C%C3%B4te+de+Liesse%2CMontr%C3%A9al+QC%2C+H4N%2CCA", "serviceProviderId": 354552, "isFranchiseDealer": true, "franchiseMake": "Lexus", "isCPO": true, "debugInfo": " / rank #: 6631 / sellerId: 2255801 / spId: 354552 / Paid Dealer: true / active partners: 630", "serviceProviderName": "Lexus Gabriel St-Laurent", "phoneNumber": "+1 825-797-0838", "phoneNumberString": "(825) 797-0838", "phoneNumberSMS": "+18559612800", "supportsSms": true, "localizedDriveTrain": "All-Wheel Drive", "localizedExteriorColor": "White", "howToShop": "PICK_UP_ONLY", "dealerLogoUrl": "https://static.cargurus.com/images/site/2024/05/31/09/59/lexus_gabriel_st-laurent-pic-9487613247143556578-200x200.jpeg", "offset": 6631, "cityFuelEconomy": {"value": 10.7, "unit": "L_PER_100KM"}, "highwayFuelEconomy": {"value": 8.1, "unit": "L_PER_100KM"}, "combinedFuelEconomy": {"value": 9.53, "unit": "L_PER_100KM"}, "localizedFuelEconomy": ["10.7", "L_PER_100KM"], "localizedFuelType": "Gasoline", "localizedCombinedFuelEconomy": "10 L/100km", "evBatteryDto": {}, "localizedDoors": "4 doors", "driveTrain": "ALL_WHEEL_DRIVE", "localizedEngineDisplayName": "275 hp 2.4L I4", "ncapOverallSafetyRating": "Not Rated", "vin": "2T2GGCEZ1NC004456", "stockNumber": "P3442"}}, {"type": "LISTING_USED_STANDARD", "data": {"id": 411406676, "inclusionType": "DEFAULT", "listingSource": "GVO-1", "listingTitle": "2016 Mercedes-Benz C-Class C 300 4MATIC", "makeName": "Mercedes-Benz", "modelName": "C-Class", "makeId": "m43", "modelId": "d66", "carYear": 2016, "trimName": "C 300 4MATIC", "localizedTransmission": "Automatic", "bodyTypeGroupId": "bg6", "bodyTypeName": "Sedan", "salesStatus": "PAYING", "options": ["Blind Spot Monitoring"], "mileage": 119224, "mileageString": "119,224", "unitMileage": {"value": 119224.0, "unit": "KILOMETERS"}, "exteriorColorName": "Black", "normalizedExteriorColor": "BLACK", "price": 18900.0, "priceString": "$18,900", "expectedPrice": 18727, "expectedPriceString": "$18,727", "priceDifferential": -173.0, "priceDifferentialString": "$173", "dealScore": 0.03875296415870949, "daysOnMarket": 27, "dealRating": "FAIR_PRICE", "isFeatured": true, "featuredTypes": ["FEATURED"], "pictureCount": 0, "originalPictureData": {"url": "https://static.cargurus.com/images/forsale/2025/03/19/06/30/2016_mercedes-benz_c-class-pic-3522729851527283286-1024x768.jpeg", "height": 768, "width": 1024}, "sellerId": 1612205, "listingPartnerId": 438, "sellerType": "DEALER", "dealerName": "Club Auto Zone", "sellerCity": "Longueuil, QC", "sellerRegion": "QC", "sellerPostalCode": "J4P 3M4", "distance": 7.1711535, "googleStaticMapUrl": "https://www.google.com/maps/dir/?api=1&destination=Club+Auto+Zone+1310+Boulevard+Taschereau%2CLongueuil+QC%2C+J4P+3M4%2CCA", "serviceProviderId": 358210, "debugInfo": " / rank #: 6632 / sellerId: 1612205 / spId: 358210 / Paid Dealer: true / active partners: 438", "serviceProviderName": "Club Auto Zone", "phoneNumber": "+1 450-390-6039", "phoneNumberString": "(450) 390-6039", "localizedDriveTrain": "All-Wheel Drive", "localizedExteriorColor": "Black", "localizedInteriorColor": "Brown (Beige)", "sellerRating": 5.0, "reviewCount": 67, "howToShop": "PICK_UP_ONLY", "dealerLogoUrl": "https://static.cargurus.com/images/site/2023/03/28/13/42/club_auto_zone-pic-14554365281210901048-200x200.jpeg", "offset": 6632, "cityFuelEconomy": {"value": 9.8, "unit": "L_PER_100KM"}, "highwayFuelEconomy": {"value": 7.6, "unit": "L_PER_100KM"}, "combinedFuelEconomy": {"value": 8.81, "unit": "L_PER_100KM"}, "localizedFuelEconomy": ["9.8", "L_PER_100KM"], "localizedFuelType": "Gasoline", "localizedCombinedFuelEconomy": "9 L/100km", "evBatteryDto": {}, "localizedDoors": "4 doors", "driveTrain": "ALL_WHEEL_DRIVE", "localizedEngineDisplayName": "241 hp 2L I4", "ncapOverallSafetyRating": "5", "vin": "55SWF4KB3GU147597", "stockNumber": "gu147597", "interiorColor": "Beige"}}, {"type": "LISTING_USED_STANDARD", "data": {"id": 412906410, "inclusionType": "DEFAULT", "listingSource": "D2C media-1", "listingTitle": "2022 Mitsubishi RVR GT AWC", "makeName": "Mitsubishi", "modelName": "RVR", "makeId": "m46", "modelId": "d2377", "carYear": 2022, "trimName": "GT AWC", "localizedTransmission": "Automatic", "bodyTypeGroupId": "bg7", "bodyTypeName": "SUV / Crossover", "salesStatus": "PAYING", "options": ["Leather Seats", "Backup Camera", "Heated Seats", "Android Auto", "CarPlay"], "mileage": 32236, "mileageString": "32,236", "unitMileage": {"value": 32236.0, "unit": "KILOMETERS"}, "exteriorColorName": "Gris", "normalizedExteriorColor": "GRAY", "price": 25992.0, "priceString": "$25,992", "expectedPrice": 26089, "expectedPriceString": "$26,089", "priceDifferential": 97.0, "priceDifferentialString": "$97", "dealScore": 0.038605495351598074, "daysOnMarket": 12, "dealRating": "FAIR_PRICE", "isFeatured": true, "featuredTypes": ["FEATURED", "PRIORITY"], "featuredPremiumType": "PRIORITY", "pictureCount": 0, "originalPictureData": {"url": "https://static.cargurus.com/images/forsale/2025/04/09/13/47/2022_mitsubishi_rvr-pic-7718995355694020053-1024x768.jpeg", "height": 768, "width": 1024}, "sellerId": 942804, "listingPartnerId": 243, "sellerType": "DEALER", "dealerName": "Blainville Mitsubishi", "sellerCity": "Blainville, QC", "sellerRegion": "QC", "sellerPostalCode": "J7C 2H2", "distance": 27.517529, "googleStaticMapUrl": "https://www.google.com/maps/dir/?api=1&destination=Blainville+Mitsubishi+418+Boul+Du+Cur%C3%A9-labelle%2CBlainville+QC%2C+J7C+2H2%2CCA", "serviceProviderId": 354956, "isFranchiseDealer": true, "franchiseMake": "Mitsubishi", "debugInfo": " / rank #: 6633 / sellerId: 942804 / spId: 354956 / Paid Dealer: true / active partners: 243", "serviceProviderName": "Blainville Mitsubishi", "phoneNumber": "+1 450-300-6353", "phoneNumberString": "(450) 300-6353", "localizedExteriorColor": "Gray", "reviewCount": 15, "howToShop": "PICK_UP_ONLY", "dealerLogoUrl": "https://static.cargurus.com/images/site/2023/03/14/16/48/blainville_mitsubishi-pic-15029190394458758777-1600x1200.jpeg", "offset": 6633, "evBatteryDto": {}, "ncapOverallSafetyRating": "Not Rated", "vin": "JA4AJVAW2NU604449", "stockNumber": "BLVL-M3922"}}, {"type": "LISTING_USED_STANDARD", "data": {"id": 411567918, "inclusionType": "DEFAULT", "listingSource": "eDealer Light-1", "listingTitle": "2018 Nissan Rogue S FWD", "makeName": "Nissan", "modelName": "Rogue", "makeId": "m12", "modelId": "d1047", "carYear": 2018, "trimName": "S FWD", "localizedTransmission": "Automatic", "bodyTypeGroupId": "bg7", "bodyTypeName": "SUV / Crossover", "salesStatus": "PAYING", "options": ["Bluetooth", "Backup Camera", "Heated Seats"], "mileage": 145300, "mileageString": "145,300", "unitMileage": {"value": 145300.0, "unit": "KILOMETERS"}, "normalizedExteriorColor": "UNKNOWN", "price": 12950.0, "priceString": "$12,950", "expectedPrice": 13020, "expectedPriceString": "$13,020", "priceDifferential": 70.0, "priceDifferentialString": "$70", "dealScore": 0.03853192117067661, "daysOnMarket": 26, "dealRating": "FAIR_PRICE", "pictureCount": 0, "originalPictureData": {"url": "https://static.cargurus.com/images/forsale/2025/03/20/16/54/2018_nissan_rogue-pic-5986225518561486563-1024x768.jpeg", "height": 768, "width": 1024}, "sellerId": 2289046, "listingPartnerId": 377, "sellerType": "DEALER", "dealerName": "Nani Auto", "sellerCity": "Montr\u00e9al, QC", "sellerRegion": "QC", "sellerPostalCode": "H1H 3J4", "distance": 12.013205, "googleStaticMapUrl": "https://www.google.com/maps/dir/?api=1&destination=Nani+Auto+10541+Av+Drapeau%2CMontr%C3%A9al+QC%2C+H1H+3J4%2CCA", "serviceProviderId": 416294, "debugInfo": " / rank #: 6634 / sellerId: 2289046 / spId: 416294 / Paid Dealer: true / active partners: 377", "serviceProviderName": "Nani Auto", "phoneNumber": "+1 833-454-9310", "phoneNumberString": "(833) 454-9310", "phoneNumberSMS": "+18559612800", "supportsSms": true, "localizedDriveTrain": "Front-Wheel Drive", "reviewCount": 13, "howToShop": "PICK_UP_ONLY", "dealerLogoUrl": "https://static.cargurus.com/images/site/2023/06/14/12/35/nani_auto-pic-9451806339938300420-200x200.jpeg", "offset": 6634, "cityFuelEconomy": {"value": 9.0, "unit": "L_PER_100KM"}, "highwayFuelEconomy": {"value": 7.1, "unit": "L_PER_100KM"}, "combinedFuelEconomy": {"value": 8.1449995, "unit": "L_PER_100KM"}, "localizedFuelEconomy": ["9.0", "L_PER_100KM"], "localizedFuelType": "Gasoline", "localizedCombinedFuelEconomy": "8 L/100km", "evBatteryDto": {}, "localizedDoors": "4 doors", "driveTrain": "FRONT_WHEEL_DRIVE", "localizedEngineDisplayName": "170 hp 2.5L I4", "ncapOverallSafetyRating": "4", "vin": "5N1AT2MT5JC850472"}}, {"type": "LISTING_USED_STANDARD", "data": {"id": 413762712, "inclusionType": "DEFAULT", "listingSource": "Magnetis-1", "listingTitle": "2016 Chrysler 200 Limited Sedan FWD", "makeName": "Chrysler", "modelName": "200", "makeId": "m23", "modelId": "d2106", "carYear": 2016, "trimName": "Limited Sedan FWD", "localizedTransmission": "Automatic", "bodyTypeGroupId": "bg6", "bodyTypeName": "Sedan", "salesStatus": "PAYING", "options": ["Bluetooth"], "mileage": 87047, "mileageString": "87,047", "unitMileage": {"value": 87047.0, "unit": "KILOMETERS"}, "exteriorColorName": "Noir", "normalizedExteriorColor": "BLACK", "price": 13525.0, "priceString": "$13,525", "expectedPrice": 13531, "expectedPriceString": "$13,531", "priceDifferential": 6.0, "priceDifferentialString": "$6", "dealScore": 0.038427649567402966, "daysOnMarket": 2, "dealRating": "FAIR_PRICE", "isFeatured": true, "featuredTypes": ["FEATURED", "PRIORITY"], "featuredPremiumType": "PRIORITY", "pictureCount": 0, "originalPictureData": {"url": "https://static.cargurus.com/images/forsale/2025/04/13/13/23/2016_chrysler_200-pic-2460296208316337265-1024x768.jpeg", "height": 768, "width": 1024}, "sellerId": 2249093, "listingPartnerId": 452, "sellerType": "DEALER", "dealerName": "Mazda Saint-Jerome", "sellerCity": "St-Jerome, QC", "sellerRegion": "QC", "sellerPostalCode": "J7Z 7L2", "distance": 43.716682, "googleStaticMapUrl": "https://www.google.com/maps/dir/?api=1&destination=Mazda+Saint-Jerome+155+Boulevard+Lachapelle%2CSt-Jerome+QC%2C+J7Z+7L2%2CCA", "serviceProviderId": 365996, "isFranchiseDealer": true, "franchiseMake": "Mazda", "debugInfo": " / rank #: 6635 / sellerId: 2249093 / spId: 365996 / Paid Dealer: true / active partners: 452", "serviceProviderName": "Mazda Saint-Jerome", "phoneNumber": "+1 450-235-7919", "phoneNumberString": "(450) 235-7919", "phoneNumberSMS": "+18559612800", "supportsSms": true, "localizedDriveTrain": "Front-Wheel Drive", "localizedExteriorColor": "Black", "sellerRating": 5.0, "reviewCount": 1, "howToShop": "PICK_UP_ONLY", "dealerLogoUrl": "https://static.cargurus.com/images/site/2024/05/24/13/26/mazda_saint-jerome-pic-9244471097882653897-200x200.jpeg", "offset": 6635, "cityFuelEconomy": {"value": 12.4, "unit": "L_PER_100KM"}, "highwayFuelEconomy": {"value": 7.4, "unit": "L_PER_100KM"}, "combinedFuelEconomy": {"value": 10.15, "unit": "L_PER_100KM"}, "localizedFuelEconomy": ["12.4", "L_PER_100KM"], "localizedFuelType": "Gasoline", "localizedCombinedFuelEconomy": "10 L/100km", "evBatteryDto": {}, "localizedDoors": "4 doors", "driveTrain": "FRONT_WHEEL_DRIVE", "localizedEngineDisplayName": "295 hp 3.6L V6", "ncapOverallSafetyRating": "5", "vin": "1C3CCCAG9GN139398", "stockNumber": "25292A"}}, {"type": "LISTING_USED_STANDARD", "data": {"id": 410377668, "inclusionType": "DEFAULT", "listingSource": "D2C media-1", "listingTitle": "2024 Buick Encore GX Sport Touring AWD", "makeName": "Buick", "modelName": "Encore GX", "makeId": "m21", "modelId": "d2901", "carYear": 2024, "trimName": "Sport Touring AWD", "localizedTransmission": "Automatic", "bodyTypeGroupId": "bg7", "bodyTypeName": "SUV / Crossover", "salesStatus": "PAYING", "options": ["Adaptive Cruise Control", "Bluetooth", "Backup Camera", "Remote Start", "CarPlay"], "mileage": 21270, "mileageString": "21,270", "unitMileage": {"value": 21270.0, "unit": "KILOMETERS"}, "exteriorColorName": "Rouge", "normalizedExteriorColor": "RED", "price": 31795.0, "priceString": "$31,795", "expectedPrice": 31795, "expectedPriceString": "$31,795", "priceDifferential": 0.0, "priceDifferentialString": "$0", "dealScore": 0.03818329948324062, "daysOnMarket": 39, "dealRating": "FAIR_PRICE", "isFeatured": true, "featuredTypes": ["FEATURED"], "pictureCount": 0, "originalPictureData": {"url": "https://static.cargurus.com/images/forsale/2025/04/14/12/56/2024_buick_encore_gx-pic-1315021302643162485-1024x768.jpeg", "height": 768, "width": 1024}, "sellerId": 1703227, "listingPartnerId": 243, "sellerType": "DEALER", "dealerName": "Chevrolet Buick GMC de LaSalle", "sellerCity": "Lasalle, QC", "sellerRegion": "QC", "sellerPostalCode": "H8N 1X9", "distance": 6.622868, "googleStaticMapUrl": "https://www.google.com/maps/dir/?api=1&destination=Chevrolet+Buick+GMC+de+LaSalle+8000+boul.+Newman%2CLasalle+QC%2C+H8N+1X9%2CCA", "serviceProviderId": 385094, "isFranchiseDealer": true, "franchiseMake": "Buick", "isCPO": true, "debugInfo": " / rank #: 6636 / sellerId: 1703227 / spId: 385094 / Paid Dealer: true / active partners: 243", "serviceProviderName": "Chevrolet Buick GMC de LaSalle", "phoneNumber": "+1 450-328-5705", "phoneNumberString": "(450) 328-5705", "localizedDriveTrain": "All-Wheel Drive", "localizedExteriorColor": "Red", "sellerRating": 5.0, "reviewCount": 31, "howToShop": "HOME_DROP_OFF", "dealerLogoUrl": "https://static.cargurus.com/images/site/2023/03/27/15/23/chevrolet_buick_gmc_de_lasalle-pic-8361250431850925619-200x200.jpeg", "offset": 6636, "cityFuelEconomy": {"value": 9.0, "unit": "L_PER_100KM"}, "highwayFuelEconomy": {"value": 8.4, "unit": "L_PER_100KM"}, "combinedFuelEconomy": {"value": 8.73, "unit": "L_PER_100KM"}, "localizedFuelEconomy": ["9.0", "L_PER_100KM"], "localizedFuelType": "Gasoline", "localizedCombinedFuelEconomy": "9 L/100km", "evBatteryDto": {}, "localizedDoors": "4 doors", "driveTrain": "ALL_WHEEL_DRIVE", "localizedEngineDisplayName": "155 hp 1.3L I3", "ncapOverallSafetyRating": "Not Rated", "vin": "KL4AMESL6RB004191", "stockNumber": "U3021"}}, {"type": "LISTING_USED_STANDARD", "data": {"id": 410065633, "inclusionType": "DEFAULT", "listingSource": "GVO-1", "listingTitle": "2019 Tesla Model 3 Standard Plus RWD", "makeName": "Tesla", "modelName": "Model 3", "makeId": "m112", "modelId": "d2475", "carYear": 2019, "trimName": "Standard Plus RWD", "localizedTransmission": "Automatic", "bodyTypeGroupId": "bg6", "bodyTypeName": "Sedan", "salesStatus": "PAYING", "options": ["Navigation System", "Backup Camera", "Remote Start", "Blind Spot Monitoring"], "mileage": 106000, "mileageString": "106,000", "unitMileage": {"value": 106000.0, "unit": "KILOMETERS"}, "exteriorColorName": "Red", "normalizedExteriorColor": "RED", "price": 22500.0, "priceString": "$22,500", "expectedPrice": 22500, "expectedPriceString": "$22,500", "priceDifferential": 0.0, "priceDifferentialString": "$0", "dealScore": 0.03806144800920219, "daysOnMarket": 42, "dealRating": "FAIR_PRICE", "isFeatured": true, "featuredTypes": ["FEATURED"], "pictureCount": 0, "originalPictureData": {"url": "https://static.cargurus.com/images/forsale/2025/03/04/03/01/2019_tesla_model_3-pic-2833464689356127139-1024x768.jpeg", "height": 768, "width": 1024}, "sellerId": 2200828, "listingPartnerId": 438, "sellerType": "DEALER", "dealerName": "Alset Cars", "sellerCity": "Montreal, QC", "sellerRegion": "QC", "sellerPostalCode": "H1G 3G7", "distance": 12.052793, "googleStaticMapUrl": "https://www.google.com/maps/dir/?api=1&destination=Alset+Cars+4847+Rue+Forest%2CMontreal+QC%2C+H1G+3G7%2CCA", "serviceProviderId": 452830, "debugInfo": " / rank #: 6637 / sellerId: 2200828 / spId: 452830 / Paid Dealer: true / active partners: 438", "serviceProviderName": "Alset Cars", "phoneNumber": "+1 855-907-4505", "phoneNumberString": "(855) 907-4505", "localizedDriveTrain": "Rear-Wheel Drive", "localizedExteriorColor": "Red", "localizedInteriorColor": "Black", "sellerRating": 5.0, "reviewCount": 1, "howToShop": "PICK_UP_ONLY", "dealerLogoUrl": "https://static.cargurus.com/images/site/2023/11/07/08/23/alset_cars-pic-1955232299776729161-200x200.jpeg", "offset": 6637, "cityFuelEconomy": {"value": 1.7, "unit": "L_PER_100KM"}, "highwayFuelEconomy": {"value": 1.9, "unit": "L_PER_100KM"}, "combinedFuelEconomy": {"value": 1.79, "unit": "L_PER_100KM"}, "localizedFuelEconomy": ["1.7", "L_PER_100KM"], "localizedFuelType": "Electric", "localizedCombinedFuelEconomy": "2 L/100km", "evBatteryDto": {"chargingTime240V": "10 hr", "capacity": "50 kWh", "range": "386 km"}, "localizedDoors": "4 doors", "driveTrain": "REAR_WHEEL_DRIVE", "localizedEngineDisplayName": "Electric", "ncapOverallSafetyRating": "5", "vin": "5YJ3E1EA6KF403278", "stockNumber": "TES-574", "interiorColor": "Black"}}, {"type": "LISTING_USED_STANDARD", "data": {"id": 402219463, "inclusionType": "DEFAULT", "listingSource": "AutoJini-1", "listingTitle": "2021 Hyundai Elantra Preferred FWD", "makeName": "Hyundai", "modelName": "Elantra", "makeId": "m28", "modelId": "d92", "carYear": 2021, "trimName": "Preferred FWD", "localizedTransmission": "Automatic", "bodyTypeGroupId": "bg6", "bodyTypeName": "Sedan", "salesStatus": "PAYING", "options": ["Alloy Wheels", "Bluetooth", "Backup Camera", "Remote Start", "Blind Spot Monitoring"], "mileage": 84573, "mileageString": "84,573", "unitMileage": {"value": 84573.0, "unit": "KILOMETERS"}, "exteriorColorName": "Blake", "normalizedExteriorColor": "UNKNOWN", "price": 19888.0, "priceString": "$19,888", "expectedPrice": 20298, "expectedPriceString": "$20,298", "priceDifferential": 410.0, "priceDifferentialString": "$410", "dealScore": 0.03802114150496677, "daysOnMarket": 140, "dealRating": "FAIR_PRICE", "isFeatured": true, "featuredTypes": ["FEATURED", "PRIORITY"], "featuredPremiumType": "PRIORITY", "pictureCount": 0, "originalPictureData": {"url": "https://static.cargurus.com/images/forsale/2024/12/19/19/35/2021_hyundai_elantra-pic-3496662566745629439-1024x768.jpeg", "height": 768, "width": 1024}, "sellerId": 1405908, "listingPartnerId": 263, "sellerType": "DEALER", "dealerName": "Desmeules Chrysler", "sellerCity": "Laval, QC", "sellerRegion": "QC", "sellerPostalCode": "H7T 2H6", "distance": 16.516623, "googleStaticMapUrl": "https://www.google.com/maps/dir/?api=1&destination=Desmeules+Chrysler+3500+Autoroute+Laval+Ouest+%28440%29%2CLaval+QC%2C+H7T+2H6%2CCA", "serviceProviderId": 358086, "isFranchiseDealer": true, "franchiseMake": "RAM", "debugInfo": " / rank #: 6638 / sellerId: 1405908 / spId: 358086 / Paid Dealer: true / active partners: 263", "serviceProviderName": "Desmeules Chrysler", "phoneNumber": "+1 450-234-9097", "phoneNumberString": "(450) 234-9097", "localizedExteriorColor": "Blake", "localizedInteriorColor": "Black", "sellerRating": 4.06, "reviewCount": 156, "isNationwideShipperDealer": true, "howToShop": "HOME_DROP_OFF", "dealerLogoUrl": "https://static.cargurus.com/images/site/2023/11/07/15/18/desmeules_chrysler-pic-17251931307222160873-200x200.jpeg", "offset": 6638, "evBatteryDto": {}, "ncapOverallSafetyRating": "Not Rated", "vin": "KMHLM4AG3MU151591", "stockNumber": "DC-D5767", "interiorColor": "Black"}}, {"type": "LISTING_USED_STANDARD", "data": {"id": 395183238, "inclusionType": "DEFAULT", "listingSource": "GVO-1", "listingTitle": "2015 Tesla Model S P85D AWD", "makeName": "Tesla", "modelName": "Model S", "makeId": "m112", "modelId": "d2039", "carYear": 2015, "trimName": "P85D AWD", "localizedTransmission": "Automatic", "bodyTypeGroupId": "bg6", "bodyTypeName": "Sedan", "salesStatus": "PAYING", "options": ["Sunroof/Moonroof", "Navigation System", "Backup Camera", "Blind Spot Monitoring"], "mileage": 151000, "mileageString": "151,000", "unitMileage": {"value": 151000.0, "unit": "KILOMETERS"}, "exteriorColorName": "White", "normalizedExteriorColor": "WHITE", "price": 29900.0, "priceString": "$29,900", "expectedPrice": 29900, "expectedPriceString": "$29,900", "priceDifferential": 0.0, "priceDifferentialString": "$0", "dealScore": 0.0380191078435933, "daysOnMarket": 223, "dealRating": "FAIR_PRICE", "isFeatured": true, "featuredTypes": ["FEATURED"], "pictureCount": 0, "originalPictureData": {"url": "https://static.cargurus.com/images/forsale/2024/09/04/02/43/2015_tesla_model_s-pic-3096212153271115989-1024x768.jpeg", "height": 768, "width": 1024}, "sellerId": 2200828, "listingPartnerId": 438, "sellerType": "DEALER", "dealerName": "Alset Cars", "sellerCity": "Montreal, QC", "sellerRegion": "QC", "sellerPostalCode": "H1G 3G7", "distance": 12.052793, "googleStaticMapUrl": "https://www.google.com/maps/dir/?api=1&destination=Alset+Cars+4847+Rue+Forest%2CMontreal+QC%2C+H1G+3G7%2CCA", "serviceProviderId": 452830, "debugInfo": " / rank #: 6639 / sellerId: 2200828 / spId: 452830 / Paid Dealer: true / active partners: 438", "serviceProviderName": "Alset Cars", "phoneNumber": "+1 855-907-4505", "phoneNumberString": "(855) 907-4505", "localizedDriveTrain": "All-Wheel Drive", "localizedExteriorColor": "White", "localizedInteriorColor": "Brown (Beige)", "sellerRating": 5.0, "reviewCount": 1, "howToShop": "PICK_UP_ONLY", "dealerLogoUrl": "https://static.cargurus.com/images/site/2023/11/07/08/23/alset_cars-pic-1955232299776729161-200x200.jpeg", "offset": 6639, "cityFuelEconomy": {"value": 2.6, "unit": "L_PER_100KM"}, "highwayFuelEconomy": {"value": 2.4, "unit": "L_PER_100KM"}, "combinedFuelEconomy": {"value": 2.51, "unit": "L_PER_100KM"}, "localizedFuelEconomy": ["2.6", "L_PER_100KM"], "localizedFuelType": "Electric", "localizedCombinedFuelEconomy": "3 L/100km", "evBatteryDto": {"chargingTime240V": "12 hr", "capacity": "85 kWh", "range": "407 km"}, "localizedDoors": "4 doors", "driveTrain": "ALL_WHEEL_DRIVE", "localizedEngineDisplayName": "Electric", "ncapOverallSafetyRating": "Not Rated", "vin": "5YJSA1H43FF082030", "stockNumber": "AL-FF082030", "interiorColor": "Beige"}}, {"type": "LISTING_USED_STANDARD", "data": {"id": 410340380, "inclusionType": "DEFAULT", "listingSource": "vAuto-0", "listingTitle": "2022 Subaru WRX Sport-tech AWD with EyeSight Package", "makeName": "Subaru", "modelName": "WRX", "makeId": "m53", "modelId": "d2292", "carYear": 2022, "trimName": "Sport-tech AWD with EyeSight Package", "localizedTransmission": "6-Speed Manual", "bodyTypeGroupId": "bg6", "bodyTypeName": "Sedan", "salesStatus": "AVAILABLE", "options": ["Sunroof/Moonroof", "Navigation System", "Alloy Wheels", "Backup Camera", "Heated Seats", "Android Auto", "CarPlay"], "mileage": 50000, "mileageString": "50,000", "unitMileage": {"value": 50000.0, "unit": "KILOMETERS"}, "normalizedExteriorColor": "UNKNOWN", "price": 31993.0, "priceString": "$31,993", "expectedPrice": 32457, "expectedPriceString": "$32,457", "priceDifferential": 464.0, "priceDifferentialString": "$464", "dealScore": 0.03800591792404877, "daysOnMarket": 39, "dealRating": "FAIR_PRICE", "pictureCount": 0, "sellerId": 2075909, "listingPartnerId": 52, "sellerType": "DEALER", "dealerName": "Mazda Val David", "sellerCity": "Val David, QC", "sellerRegion": "QC", "sellerPostalCode": "J0T 2N0", "distance": 98.58238, "googleStaticMapUrl": "https://www.google.com/maps/dir/?api=1&destination=Mazda+Val+David+1004+Route+117%2CVal+David+QC%2C+J0T+2N0%2CCA", "serviceProviderId": 365951, "isFranchiseDealer": true, "franchiseMake": "Mazda", "debugInfo": " / rank #: 6640 / sellerId: 2075909 / spId: 365951 / active partners: 52", "serviceProviderName": "Mazda Val David", "useAnonymousContactEmail": true, "howToShop": "PICK_UP_ONLY", "offset": 6640, "evBatteryDto": {}, "ncapOverallSafetyRating": "Not Rated", "vin": "JF1VBAL60N9018724", "stockNumber": "B2548"}}, {"type": "LISTING_USED_STANDARD", "data": {"id": 393349944, "inclusionType": "DEFAULT", "listingSource": "GVO-1", "listingTitle": "2016 Volkswagen Touareg AWD Highline", "makeName": "Volkswagen", "modelName": "Touareg", "makeId": "m55", "modelId": "d205", "carYear": 2016, "trimName": "AWD Highline", "localizedTransmission": "Automatic", "bodyTypeGroupId": "bg7", "bodyTypeName": "SUV / Crossover", "salesStatus": "PAYING", "options": ["Sunroof/Moonroof", "Navigation System", "Backup Camera"], "mileage": 152966, "mileageString": "152,966", "unitMileage": {"value": 152966.0, "unit": "KILOMETERS"}, "exteriorColorName": "Grey", "normalizedExteriorColor": "GRAY", "price": 15900.0, "priceString": "$15,900", "expectedPrice": 15900, "expectedPriceString": "$15,900", "priceDifferential": 0.0, "priceDifferentialString": "$0", "dealScore": 0.03799503223456471, "daysOnMarket": 244, "dealRating": "FAIR_PRICE", "isFeatured": true, "featuredTypes": ["FEATURED"], "pictureCount": 0, "originalPictureData": {"url": "https://static.cargurus.com/images/forsale/2024/08/14/03/29/2016_volkswagen_touareg-pic-2313752462787605850-1024x768.jpeg", "height": 768, "width": 1024}, "sellerId": 2200828, "listingPartnerId": 438, "sellerType": "DEALER", "dealerName": "Alset Cars", "sellerCity": "Montreal, QC", "sellerRegion": "QC", "sellerPostalCode": "H1G 3G7", "distance": 12.052793, "googleStaticMapUrl": "https://www.google.com/maps/dir/?api=1&destination=Alset+Cars+4847+Rue+Forest%2CMontreal+QC%2C+H1G+3G7%2CCA", "serviceProviderId": 452830, "debugInfo": " / rank #: 6641 / sellerId: 2200828 / spId: 452830 / Paid Dealer: true / active partners: 438", "serviceProviderName": "Alset Cars", "phoneNumber": "+1 855-907-4505", "phoneNumberString": "(855) 907-4505", "localizedExteriorColor": "Gray", "localizedInteriorColor": "Black", "sellerRating": 5.0, "reviewCount": 1, "howToShop": "PICK_UP_ONLY", "dealerLogoUrl": "https://static.cargurus.com/images/site/2023/11/07/08/23/alset_cars-pic-1955232299776729161-200x200.jpeg", "offset": 6641, "evBatteryDto": {}, "ncapOverallSafetyRating": "Not Rated", "vin": "WVGEF9BPXGD011749", "stockNumber": "TH-216", "interiorColor": "Black"}}, {"type": "LISTING_USED_STANDARD", "data": {"id": 405782777, "inclusionType": "DEFAULT", "listingSource": "info@convertus.com-1", "listingTitle": "2020 Land Rover Range Rover Evoque P300 R-Dynamic HSE AWD", "makeName": "Land Rover", "modelName": "Range Rover Evoque", "makeId": "m35", "modelId": "d2121", "carYear": 2020, "trimName": "P300 R-Dynamic HSE AWD", "localizedTransmission": "Automatic", "bodyTypeGroupId": "bg7", "bodyTypeName": "SUV / Crossover", "salesStatus": "PAYING", "options": ["Leather Seats", "Sunroof/Moonroof", "Power Package", "Adaptive Cruise Control", "Bluetooth", "Premium Wheels", "Backup Camera", "Blind Spot Monitoring", "Parking Sensors", "Heated Seats", "Android Auto", "CarPlay"], "mileage": 44925, "mileageString": "44,925", "unitMileage": {"value": 44925.0, "unit": "KILOMETERS"}, "exteriorColorName": "Red", "normalizedExteriorColor": "RED", "price": 35995.0, "priceString": "$35,995", "expectedPrice": 35957, "expectedPriceString": "$35,957", "priceDifferential": -38.0, "priceDifferentialString": "$38", "dealScore": 0.03782810585077734, "daysOnMarket": 95, "dealRating": "FAIR_PRICE", "pictureCount": 0, "originalPictureData": {"url": "https://static.cargurus.com/images/forsale/2025/03/06/07/10/2020_land_rover_range_rover_evoque-pic-1666149255139975574-1024x768.jpeg", "height": 768, "width": 1024}, "sellerId": 2050847, "listingPartnerId": 291, "sellerType": "DEALER", "dealerName": "Joliette Dodge Chrysler Ltee", "sellerCity": "Joliette, QC", "sellerRegion": "QC", "sellerPostalCode": "J6E 8S9", "distance": 59.912296, "googleStaticMapUrl": "https://www.google.com/maps/dir/?api=1&destination=Joliette+Dodge+Chrysler+Ltee+305+Rue+Cur%C3%A9+Majeau%2CJoliette+QC%2C+J6E+8S9%2CCA", "serviceProviderId": 356084, "isFranchiseDealer": true, "franchiseMake": "RAM", "debugInfo": " / rank #: 6642 / sellerId: 2050847 / spId: 356084 / Paid Dealer: true / active partners: 291", "serviceProviderName": "Joliette Dodge Chrysler Ltee", "phoneNumber": "+1 450-600-4108", "phoneNumberString": "(450) 600-4108", "localizedDriveTrain": "All-Wheel Drive", "localizedExteriorColor": "Red", "sellerRating": 4.64, "reviewCount": 66, "isNationwideShipperDealer": true, "howToShop": "PICK_UP_ONLY", "dealerLogoUrl": "https://static.cargurus.com/images/site/2024/07/08/10/27/joliette_dodge_chrysler_ltee-pic-2889148723815046737-200x200.jpeg", "offset": 6642, "cityFuelEconomy": {"value": 11.8, "unit": "L_PER_100KM"}, "highwayFuelEconomy": {"value": 8.7, "unit": "L_PER_100KM"}, "combinedFuelEconomy": {"value": 10.405, "unit": "L_PER_100KM"}, "localizedFuelEconomy": ["11.8", "L_PER_100KM"], "localizedFuelType": "Gasoline", "localizedCombinedFuelEconomy": "10 L/100km", "evBatteryDto": {}, "localizedDoors": "4 doors", "driveTrain": "ALL_WHEEL_DRIVE", "localizedEngineDisplayName": "296 hp 2L I4", "ncapOverallSafetyRating": "Not Rated", "vin": "SALZM2GX4LH117699", "stockNumber": "U6507"}}, {"type": "LISTING_USED_STANDARD", "data": {"id": 406124778, "inclusionType": "DEFAULT", "listingSource": "GVO-1", "listingTitle": "2019 Chrysler Pacifica Hybrid Limited FWD", "makeName": "Chrysler", "modelName": "Pacifica Hybrid", "makeId": "m23", "modelId": "d2478", "carYear": 2019, "trimName": "Limited FWD", "localizedTransmission": "Automatic", "bodyTypeGroupId": "bg4", "bodyTypeName": "Minivan", "salesStatus": "PAYING", "options": ["Leather Seats", "Sunroof/Moonroof", "Navigation System", "Adaptive Cruise Control", "DVD Entertainment System", "Alloy Wheels", "Third Row Seating", "Blind Spot Monitoring", "Parking Sensors", "Heated Seats", "Multi Zone Climate Control", "Bluetooth", "Backup Camera", "Remote Start"], "mileage": 129301, "mileageString": "129,301", "unitMileage": {"value": 129301.0, "unit": "KILOMETERS"}, "exteriorColorName": "Black", "normalizedExteriorColor": "BLACK", "price": 26990.0, "priceString": "$26,990", "expectedPrice": 27690, "expectedPriceString": "$27,690", "priceDifferential": 700.0, "priceDifferentialString": "$700", "dealScore": 0.037687931454088164, "daysOnMarket": 90, "dealRating": "FAIR_PRICE", "isFeatured": true, "featuredTypes": ["FEATURED", "PRIORITY"], "featuredPremiumType": "PRIORITY", "pictureCount": 0, "originalPictureData": {"url": "https://static.cargurus.com/images/forsale/2025/02/06/05/24/2019_chrysler_pacifica_hybrid-pic-7827651028547375155-1024x768.jpeg", "height": 768, "width": 1024}, "sellerId": 1267119, "listingPartnerId": 438, "sellerType": "DEALER", "dealerName": "Complexe Auto Plus Inc", "sellerCity": "Saint-J\u00e9r\u00f4me, QC", "sellerRegion": "QC", "sellerPostalCode": "J7Z 3A1", "distance": 43.793877, "googleStaticMapUrl": "https://www.google.com/maps/dir/?api=1&destination=Complexe+Auto+Plus+Inc+380+Boulevard+Lachapelle%2CSaint-J%C3%A9r%C3%B4me+QC%2C+J7Z+3A1%2CCA", "serviceProviderId": 359826, "debugInfo": " / rank #: 6643 / sellerId: 1267119 / spId: 359826 / Paid Dealer: true / active partners: 438", "serviceProviderName": "Complexe Auto Plus Inc", "phoneNumber": "+1 450-924-2744", "phoneNumberString": "(450) 924-2744", "localizedDriveTrain": "Front-Wheel Drive", "localizedExteriorColor": "Black", "localizedInteriorColor": "Black", "sellerRating": 3.81, "reviewCount": 126, "isNationwideShipperDealer": true, "howToShop": "PICK_UP_ONLY", "dealerLogoUrl": "https://static.cargurus.com/images/site/2016/12/29/14/52/complexe_auto_plus_inc-pic-1405928412345144532-200x200.jpeg", "offset": 6643, "cityFuelEconomy": {"value": 2.7, "unit": "L_PER_100KM"}, "highwayFuelEconomy": {"value": 3.1, "unit": "L_PER_100KM"}, "combinedFuelEconomy": {"value": 2.8799999, "unit": "L_PER_100KM"}, "localizedFuelEconomy": ["2.7", "L_PER_100KM"], "localizedFuelType": "Hybrid", "localizedCombinedFuelEconomy": "3 L/100km", "evBatteryDto": {"chargingTime240V": "2 hr", "capacity": "16 kWh", "range": "53 km"}, "localizedDoors": "4 doors", "driveTrain": "FRONT_WHEEL_DRIVE", "localizedEngineDisplayName": "3.6L V6 Hybrid", "ncapOverallSafetyRating": "5", "vin": "2C4RC1N79KR590895", "stockNumber": "16423", "interiorColor": "Black"}}], "pageNumber": 289, "pageReceipt": "eyJwYWdlQWxpZ25tZW50IjpbMjAsMjNdLCJzZWVuU3BvbnNvcmVkTGlzdGluZ0lkcyI6WzQxMTkyNzU0OCw0MDMxMDkzMTcsNDA4NzMzMDcxLDM2NzY2MDYyMyw0MDgwOTE4NDVdfQ=="}